sddk/__init__ (1).py
sddk/__init__.py
sddk-3.9.dist-info/LICENCE
sddk-3.9.dist-info/METADATA
sddk-3.9.dist-info/PKG-INFO (1)
sddk-3.9.dist-info/WHEEL
sddk-3.9.dist-info/top_level.txt
sddk-3.9.dist-info/RECORD
