Metadata-Version: 2.1
Name: sddk
Version: 3.9
Summary: A package to access sciencedata.dk
Home-page: https://github.com/sdam-au/sddk
Author: Vojtech Kase
Author-email: vojtech.kase@gmail.com
Classifier: Programming Language :: Python :: 3
Classifier: License :: OSI Approved :: MIT License
Classifier: Operating System :: OS Independent
Requires-Python: >=3.4
License-File: LICENCE
Requires-Dist: pyarrow
Requires-Dist: plotly
Requires-Dist: beautifulsoup4 (>=4)
Requires-Dist: pandas (>=1)
Requires-Dist: numpy (>=1)
Requires-Dist: requests (>=2)
Requires-Dist: matplotlib (>=3.3.4)
Requires-Dist: geopandas
Requires-Dist: shapely
